tccedvs.py
tccedvs-0.2.dist-info/LICENSE
tccedvs-0.2.dist-info/WHEEL
tccedvs-0.2.dist-info/METADATA
tccedvs-0.2.dist-info/RECORD
