Metadata-Version: 2.1
Name: tccedvs
Version: 0.2
Summary: 2 Club Cluster Edge Deletion with Vertex Splitting
Author-email: Sergio Thoumi <sergio.thoumi@lau.edu>
Requires-Python: >=3.10
Classifier: License :: OSI Approved :: MIT License
Requires-Dist: networkx
